imgmatch/__init__.py
imgmatch/main.py
imgmatch-0.1.0.dist-info/METADATA
imgmatch-0.1.0.dist-info/WHEEL
imgmatch-0.1.0.dist-info/entry_points.txt
imgmatch-0.1.0.dist-info/RECORD
