Metadata-Version: 2.1
Name: imgmatch
Version: 0.1.0
Summary: imgmatch: Image Template Matching Tool
License: MIT
Author: Zeeshan Khan
Author-email: zkhan1093@gmail.com
Requires-Python: >=3.10,<4.0
Classifier: License :: OSI Approved :: MIT License
Classifier: Programming Language :: Python :: 3
Classifier: Programming Language :: Python :: 3.10
Classifier: Programming Language :: Python :: 3.11
Requires-Dist: click (>=8.1.7,<9.0.0)
Requires-Dist: numpy (>=1.26.2,<2.0.0)
Requires-Dist: opencv-python (>=4.8.1.78,<5.0.0.0)
Requires-Dist: rich (>=13.7.0,<14.0.0)
Requires-Dist: update (>=0.0.1,<0.0.2)
